cleen/__init__.py
cleen/cluster/__init__.py
cleen/learner/__init__.py
cleen/segmenter/__init__.py
cleen-0.0.1.dist-info/LICENSE
cleen-0.0.1.dist-info/METADATA
cleen-0.0.1.dist-info/WHEEL
cleen-0.0.1.dist-info/RECORD
