Metadata-Version: 2.1
Name: cleen
Version: 0.0.1
Summary: Unveiling Insights Through Automated Feature Range Analysis.
License: MIT
Author: Yin Cheng
Author-email: yin.sjtu@gmail.com
Requires-Python: >=3.9,<4.0
Classifier: License :: OSI Approved :: MIT License
Classifier: Programming Language :: Python :: 3
Classifier: Programming Language :: Python :: 3.9
Classifier: Programming Language :: Python :: 3.10
Classifier: Programming Language :: Python :: 3.11
Classifier: Programming Language :: Python :: 3.12
Requires-Dist: lightgbm (>=4.3.0,<5.0.0)
Requires-Dist: paradance (>=0.4.21,<0.5.0)
